{"montagu":{"package":["montagu"],"version":["0.1.5"],"sha":["b1d0f9afa7e3de5e4a9cb53ce304f9919bfb5350"],"date":["2017-12-15 14:59:36"],"str":["vimc/montagu-r@master"]},"orderly":{"package":["orderly"],"version":["0.3.3"],"sha":["988b7fb6aa9ada3654434629dfdf3537cefe29d9"],"date":["2017-11-21 12:22:11"],"str":["vimc/orderly@master"]},"vaultr":{"package":["vaultr"],"version":["0.0.2"],"sha":["4d74f60fabfceecc793122d9ee1ed16da6656b6b"],"date":["2017-11-21 12:22:11"],"str":["vimc/vaultr@master"]},"jenner":{"package":["jenner"],"version":["0.0.6"],"sha":["dfe99cac2e94f3cffc00cc77440426fa84be7e78"],"date":["2017-11-22 15:51:36"],"str":["vimc/jenner@master"]}}
